mneprep/__init__.py
mneprep/__main__.py
mneprep/popup_messages.py
mneprep/io/__init__.py
mneprep/io/load_data.py
mneprep/io/save_data.py
mneprep/plot_classes/__init__.py
mneprep/plot_classes/epo_evoked_tab.py
mneprep/plot_classes/pick_chs_dialog.py
mneprep/plot_classes/plot_window.py
mneprep/plot_classes/psd_tab.py
mneprep/plot_classes/time_series_tab.py
mneprep/prep_classes/__init__.py
mneprep/prep_classes/bad_ch_options.py
mneprep/prep_classes/baseline_options.py
mneprep/prep_classes/epochs_options.py
mneprep/prep_classes/filter_options.py
mneprep/prep_classes/ica_options.py
mneprep/prep_classes/line_noise_options.py
mneprep/prep_classes/main_window.py
mneprep/prep_classes/resample_options.py
mneprep/prep_functions/__init__.py
mneprep/prep_functions/bad_chs.py
mneprep/prep_functions/baseline.py
mneprep/prep_functions/check_channel_types.py
mneprep/prep_functions/epochs.py
mneprep/prep_functions/filters.py
mneprep/prep_functions/ica.py
mneprep/prep_functions/pipeline_dicts.py
mneprep/prep_functions/reference.py
mneprep/prep_functions/resample.py
mneprep-0.0.6.dist-info/LICENSE.txt
mneprep-0.0.6.dist-info/METADATA
mneprep-0.0.6.dist-info/WHEEL
mneprep-0.0.6.dist-info/top_level.txt
mneprep-0.0.6.dist-info/RECORD
